symphony_fairvis/__init__.py
symphony_fairvis/_frontend.py
symphony_fairvis/_version.py
symphony_fairvis/widget.py
symphony_fairvis/labextension/build_log.json
symphony_fairvis/labextension/package.json
symphony_fairvis/labextension/static/lib_index_js.8712f6024a348b11476f.js
symphony_fairvis/labextension/static/lib_index_js.8712f6024a348b11476f.js.map
symphony_fairvis/labextension/static/lib_index_js.8e2e44b4474da2cd5376.js
symphony_fairvis/labextension/static/lib_index_js.8e2e44b4474da2cd5376.js.map
symphony_fairvis/labextension/static/remoteEntry.0b90e5b65c0d860b5c71.js
symphony_fairvis/labextension/static/remoteEntry.0b90e5b65c0d860b5c71.js.map
symphony_fairvis/labextension/static/remoteEntry.d85f452ad0053a043d5a.js
symphony_fairvis/labextension/static/remoteEntry.d85f452ad0053a043d5a.js.map
symphony_fairvis/labextension/static/style.js
symphony_fairvis/nbextension/extension.js
symphony_fairvis/nbextension/index.js
symphony_fairvis/standalone/widgets/SymphonyFairVis.js
symphony_fairvis/standalone/widgets/SymphonyFairVis.js.map
symphony_fairvis-1.0.2.data/data/etc/jupyter/nbconfig/notebook.d/symphony_fairvis.json
symphony_fairvis-1.0.2.data/data/share/jupyter/labextensions/symphony-fairvis/build_log.json
symphony_fairvis-1.0.2.data/data/share/jupyter/labextensions/symphony-fairvis/install.json
symphony_fairvis-1.0.2.data/data/share/jupyter/labextensions/symphony-fairvis/package.json
symphony_fairvis-1.0.2.data/data/share/jupyter/labextensions/symphony-fairvis/static/lib_index_js.8e2e44b4474da2cd5376.js
symphony_fairvis-1.0.2.data/data/share/jupyter/labextensions/symphony-fairvis/static/lib_index_js.8e2e44b4474da2cd5376.js.map
symphony_fairvis-1.0.2.data/data/share/jupyter/labextensions/symphony-fairvis/static/remoteEntry.d85f452ad0053a043d5a.js
symphony_fairvis-1.0.2.data/data/share/jupyter/labextensions/symphony-fairvis/static/remoteEntry.d85f452ad0053a043d5a.js.map
symphony_fairvis-1.0.2.data/data/share/jupyter/labextensions/symphony-fairvis/static/style.js
symphony_fairvis-1.0.2.dist-info/LICENSE.txt
symphony_fairvis-1.0.2.dist-info/METADATA
symphony_fairvis-1.0.2.dist-info/WHEEL
symphony_fairvis-1.0.2.dist-info/top_level.txt
symphony_fairvis-1.0.2.dist-info/RECORD
